ChangeLog
LICENSE
MANIFEST.in
README.md
dot_parser.py
pydot.py
requirements.txt
setup.cfg
setup.py
pydotz.egg-info/PKG-INFO
pydotz.egg-info/SOURCES.txt
pydotz.egg-info/dependency_links.txt
pydotz.egg-info/requires.txt
pydotz.egg-info/top_level.txt
test/pydot_unittest.py
test/graphs/ER.dot
test/graphs/Heawood.dot
test/graphs/KW91.dot
test/graphs/Latin1.dot
test/graphs/NaN.dot
test/graphs/Petersen.dot
test/graphs/a.dot
test/graphs/abstract.dot
test/graphs/alf.dot
test/graphs/arrows.dot
test/graphs/arrowsize.dot
test/graphs/awilliams.dot
test/graphs/b.dot
test/graphs/b102.dot
test/graphs/b106.dot
test/graphs/b117.dot
test/graphs/b123.dot
test/graphs/b124.dot
test/graphs/b135.dot
test/graphs/b143.dot
test/graphs/b145.dot
test/graphs/b146.dot
test/graphs/b155.dot
test/graphs/b22.dot
test/graphs/b29.dot
test/graphs/b3.dot
test/graphs/b33.dot
test/graphs/b34.dot
test/graphs/b36.dot
test/graphs/b491.dot
test/graphs/b51.dot
test/graphs/b53.dot
test/graphs/b545.dot
test/graphs/b56.dot
test/graphs/b57.dot
test/graphs/b60.dot
test/graphs/b62.dot
test/graphs/b68.dot
test/graphs/b69.dot
test/graphs/b7.dot
test/graphs/b71.dot
test/graphs/b73.dot
test/graphs/b73a.dot
test/graphs/b76.dot
test/graphs/b77.dot
test/graphs/b786.dot
test/graphs/b79.dot
test/graphs/b80.dot
test/graphs/b80a.dot
test/graphs/b85.dot
test/graphs/b94.dot
test/graphs/b993.dot
test/graphs/bad.dot
test/graphs/badvoro.dot
test/graphs/big.dot
test/graphs/biglabel.dot
test/graphs/cairo.dot
test/graphs/center.dot
test/graphs/clover.dot
test/graphs/clust.dot
test/graphs/clust1.dot
test/graphs/clust2.dot
test/graphs/clust3.dot
test/graphs/clust4.dot
test/graphs/clust5.dot
test/graphs/color.dot
test/graphs/colors.dot
test/graphs/colorscheme.dot
test/graphs/compound.dot
test/graphs/crazy.dot
test/graphs/ctext.dot
test/graphs/d.dot
test/graphs/dd.dot
test/graphs/decorate.dot
test/graphs/dfa.dot
test/graphs/dir.dot
test/graphs/dpd.dot
test/graphs/edgeclip.dot
test/graphs/fig6.dot
test/graphs/fsm.dot
test/graphs/grammar.dot
test/graphs/hashtable.dot
test/graphs/honda-tokoro.dot
test/graphs/html.dot
test/graphs/html2.dot
test/graphs/in.dot
test/graphs/jcctree.dot
