Metadata-Version: 2.1
Name: pydotz
Version: 1.5.1
Summary: Python interface to Graphviz's Dot (updated fork of pydot)
Home-page: https://github.com/sytelus/pydotz
Author: Ero Carrera
Author-email: ero@dkbza.org
Maintainer: Shital Shah
Maintainer-email: sytelus@gmail.com
License: MIT
Keywords: graphviz dot graphs visualization pydot
Platform: UNKNOWN
Classifier: Development Status :: 5 - Production/Stable
Classifier: Intended Audience :: Developers
Classifier: Intended Audience :: Science/Research
Classifier: License :: OSI Approved :: MIT License
Classifier: Natural Language :: English
Classifier: Operating System :: OS Independent
Classifier: Programming Language :: Python :: 2
Classifier: Programming Language :: Python :: 2.7
Classifier: Programming Language :: Python :: 3
Classifier: Programming Language :: Python :: 3.4
Classifier: Programming Language :: Python :: 3.5
Classifier: Programming Language :: Python :: 3.6
Classifier: Programming Language :: Python :: 3.7
Classifier: Topic :: Scientific/Engineering :: Visualization
Classifier: Topic :: Software Development :: Libraries :: Python Modules
Requires-Python: >=2.7, !=3.0.*, !=3.1.*, !=3.2.*, !=3.3.*
